LICENSE
README.md
setup.py
vorlang/__init__.py
vorlang/main.py
vorlang/system.py
vorlang.egg-info/PKG-INFO
vorlang.egg-info/SOURCES.txt
vorlang.egg-info/dependency_links.txt
vorlang.egg-info/entry_points.txt
vorlang.egg-info/requires.txt
vorlang.egg-info/top_level.txt